srmp/__init__.py
srmp/planner_interface.py
srmp-0.1.0.dist-info/METADATA
srmp-0.1.0.dist-info/WHEEL
srmp-0.1.0.dist-info/licenses/LICENSE
srmp-0.1.0.dist-info/RECORD
