Metadata-Version: 2.1
Name: srmp
Version: 0.1.0
Summary: Python bindings for Search-Based Robot Motion Planning (SRMP)
Author-Email: Itamar Mishani <imishani@gmail.com>, Yorai Shaoul <yorai.shaoul@gmail.com>, Ramkumar Natarajan <nrkumar93@gmail.com>
Maintainer-Email: Ramkumar Natarajan <nrkumar93@gmail.com>
License: AGPL-3.0
Classifier: Development Status :: 4 - Beta
Classifier: License :: OSI Approved :: GNU Affero General Public License v3 or later (AGPLv3+)
Classifier: Programming Language :: C++
Classifier: Programming Language :: Python :: 3
Classifier: Programming Language :: Python :: 3.8
Classifier: Programming Language :: Python :: 3.9
Classifier: Programming Language :: Python :: 3.10
Classifier: Programming Language :: Python :: 3.11
Classifier: Operating System :: POSIX :: Linux
Classifier: Topic :: Scientific/Engineering :: Artificial Intelligence
